argparse_tui/__init__.py
argparse_tui/__version__.py
argparse_tui/argparse.py
argparse_tui/constants.py
argparse_tui/detect_run_string.py
argparse_tui/py.typed
argparse_tui/run_command.py
argparse_tui/schemas.py
argparse_tui/tui.py
argparse_tui/tui.scss
argparse_tui/widgets/__init__.py
argparse_tui/widgets/about.py
argparse_tui/widgets/command_info.py
argparse_tui/widgets/command_tree.py
argparse_tui/widgets/form.py
argparse_tui/widgets/multiple_choice.py
argparse_tui/widgets/parameter_controls.py
argparse_tui-0.3.1.dist-info/LICENSE
argparse_tui-0.3.1.dist-info/WHEEL
argparse_tui-0.3.1.dist-info/METADATA
argparse_tui-0.3.1.dist-info/RECORD
